{
  "version": "1.0",
  "backup_time": "2026-01-30T17:33:15.568068",
  "data": [
    {
      "id": 1,
      "name": "预付款比例红线",
      "description": "控制预付款比例，降低资金风险",
      "content": "\n【预付款比例红线规则】\n\n1. **基本原则**：预付款比例原则上不得超过合同总额的30%。\n\n2. **特殊情况例外**：\n   - 对于大型设备采购或工程建设，经特别批准可放宽至50%\n   - 必须有明确的付款节点和验收标准\n\n3. **审查要点**：\n   - 检查合同中预付款比例是否超过30%（或经批准的50%）\n   - 预付款是否与明确的里程碑或验收条件挂钩\n   - 是否存在\"全额预付\"等高风险条款\n\n4. **风险等级**: Critical（红线）\n\n5. **建议措辞**：\n   - \"预付款比例过高，建议不超过合同总额的30%\"\n   - \"预付款应与明确的验收节点挂钩\"\n",
      "is_active": 1,
      "created_at": "2026-01-27 09:53:08.026831",
      "rule_category": "custom",
      "creator_id": null,
      "priority": 0,
      "is_system": 0
    },
    {
      "id": 2,
      "name": "争议解决条款",
      "description": "确保争议解决方式对公司有利",
      "content": "\n【争议解决条款规则】\n\n1. **优先顺序**：\n   - 第一选择：约定在\"甲方所在地法院\"诉讼\n   - 第二选择：约定在特定仲裁委员会（如北京仲裁委员会、上海仲裁委员会）仲裁\n   - 禁止接受：被告所在地法院、对方所在地仲裁\n\n2. **审查要点**：\n   - 检查争议解决条款是否明确\n   - 管辖法院/仲裁机构是否对公司有利\n   - 是否存在\"或裁或审\"等无效约定\n\n3. **风险等级**: High\n\n4. **建议措辞**：\n   - \"因本合同引起的争议，应提交甲方所在地人民法院诉讼解决\"\n   - \"争议提交北京仲裁委员会，按照申请仲裁时该会现行有效的仲裁规则进行仲裁\"\n",
      "is_active": 1,
      "created_at": "2026-01-27 09:53:08.029024",
      "rule_category": "custom",
      "creator_id": null,
      "priority": 0,
      "is_system": 0
    },
    {
      "id": 3,
      "name": "违约责任完整性",
      "description": "确保双方违约责任对等且具体",
      "content": "\n【违约责任完整性规则】\n\n1. **核心原则**：双方违约责任应当对等、具体、可执行。\n\n2. **审查要点**：\n   - 是否明确约定了双方的违约情形\n   - 违约金计算方式是否具体（如：每日万分之五）\n   - 是否存在\"甲方不承担违约责任\"等不对等条款\n   - 违约金是否过高或过低（一般不超过合同总额的30%）\n\n3. **红线预警**：\n   - 仅约定乙方违约责任，甲方无违约责任\n   - 违约金条款模糊不清（如\"承担相应责任\"）\n   - 免责条款过宽（如\"甲方对任何损失不承担责任\"）\n\n4. **风险等级**: High（红线预警）\n\n5. **建议措辞**：\n   - \"双方均应严格履行合同义务，任何一方违约应承担相应违约责任\"\n   - \"违约方应向守约方支付违约金，计算方式为：[具体计算公式]\"\n",
      "is_active": 1,
      "created_at": "2026-01-27 09:53:08.030951",
      "rule_category": "custom",
      "creator_id": null,
      "priority": 0,
      "is_system": 0
    },
    {
      "id": 4,
      "name": "合同性质与类型认定",
      "description": "明确合同法律性质，确保适用正确法规",
      "content": "\n【合同性质与类型认定规则】\n\n1. **典型合同类型**（基于《民法典》）：\n   - 买卖合同、供用电水气热合同、赠与合同\n   - 借款合同、保证合同、租赁合同、融资租赁合同\n   - 保理合同、承揽合同、建设工程合同\n   - 运输合同、技术合同、保管合同、仓储合同\n   - 委托合同、物业服务合同、行纪合同、中介合同、合伙合同\n\n2. **审查要点**：\n   - 通读全文，判断合同属于哪种典型合同\n   - 如不属于典型合同，应明确其基础法律关系\n   - 检查合同名称与实际内容是否一致\n\n3. **特殊风险**：\n   - \"名为合作实为借贷\"：需警惕虚假表示\n   - \"名为买卖实为融资\"：警惕融资性贸易风险\n\n4. **风险等级**: Medium\n\n5. **建议措辞**：\n   - \"本合同性质为[XXX]合同，应遵循《民法典》关于[XXX]合同的专门规定\"\n   - \"合同名称与内容不一致，建议修改合同名称以反映实际法律关系\"\n",
      "is_active": 1,
      "created_at": "2026-01-27 09:53:08.032734",
      "rule_category": "custom",
      "creator_id": null,
      "priority": 0,
      "is_system": 0
    },
    {
      "id": 5,
      "name": "条款完备性检查",
      "description": "确保核心条款齐备",
      "content": "\n【条款完备性检查规则】\n\n1. **必备条款清单**：\n   - 标的物/服务内容\n   - 数量与质量标准\n   - 价款或报酬\n   - 履行期限、地点、方式\n   - 违约责任\n   - 争议解决方式\n\n2. **审查要点**：\n   - 逐一核对必备条款是否齐备\n   - 检查是否存在\"另行协商\"等模糊表述导致条款缺失\n   - 关键条款是否具体明确\n\n3. **常见缺失**：\n   - 质量标准不明确\n   - 履行期限模糊\n   - 违约责任约定不清\n\n4. **风险等级**: Medium\n\n5. **建议措辞**：\n   - \"建议补充明确[XXX]的具体标准\"\n   - \"建议约定明确的履行期限\"\n",
      "is_active": 1,
      "created_at": "2026-01-27 09:53:08.034345",
      "rule_category": "custom",
      "creator_id": null,
      "priority": 0,
      "is_system": 0
    },
    {
      "id": 6,
      "name": "条款逻辑一致性",
      "description": "检查条款间是否存在矛盾或歧义",
      "content": "\n【条款逻辑一致性规则】\n\n1. **矛盾检查**：\n   - 同一事项在不同条款中表述是否一致\n   - 数字、日期、金额等关键信息是否前后一致\n   - 权利义务是否对等\n\n2. **常见矛盾类型**：\n   - 价格条款：前文\"固定总价\"，后文\"按实结算\"\n   - 期限条款：前文\"1年有效期\"，后文\"2年质保期\"\n   - 支付条款：前文\"月结\"，后文\"季结\"\n\n3. **歧义检查**：\n   - 语言表述是否清晰\n   - 是否存在多义词导致理解困难\n   - 专业术语是否有定义\n\n4. **风险等级**: Medium\n\n5. **建议措辞**：\n   - \"条款[XXX]与[YYY]存在矛盾，建议统一\"\n   - \"表述存在歧义，建议明确[XXX]的具体含义\"\n",
      "is_active": 1,
      "created_at": "2026-01-27 09:53:08.036504",
      "rule_category": "custom",
      "creator_id": null,
      "priority": 0,
      "is_system": 0
    },
    {
      "id": 7,
      "name": "金额准确性核查",
      "description": "确保金额表述准确无误",
      "content": "\n【金额准确性核查规则】\n\n1. **核查要点**：\n   - 大小写金额是否一致\n   - 计算公式是否正确\n   - 单位是否明确（元/万元/美元）\n   - 是否含税（增值税税率）\n\n2. **常见错误**：\n   - 大小写不一致\n   - 计算错误（如：单价×数量≠总价）\n   - 税费承担约定不明\n\n3. **红线预警**：\n   - 金额表述模糊（如\"相关费用\"、\"合理费用\"）\n   - 费用承担方不明确\n\n4. **风险等级**: High（金额错误）\n\n5. **建议措辞**：\n   - \"大小写金额不一致，请核实\"\n   - \"建议明确费用承担方\"\n   - \"建议明确是否含税及税率\"\n",
      "is_active": 1,
      "created_at": "2026-01-27 09:53:08.038120",
      "rule_category": "custom",
      "creator_id": null,
      "priority": 0,
      "is_system": 0
    },
    {
      "id": 8,
      "name": "主体资格与合法性",
      "description": "确保合同主体具备相应资质",
      "content": "\n【主体资格与合法性规则】\n\n1. **审查要点**：\n   - 合同主体是否具备签署该类合同的资质\n   - 是否需要特殊许可（如建筑资质、特许经营许可）\n   - 是否存在超越经营范围的情况\n\n2. **高风险行业**：\n   - 建筑工程：需检查建筑业企业资质证书\n   - 医疗器械：需检查医疗器械经营许可证\n   - 教育培训：需检查办学许可证\n   - 金融业务：需检查金融许可证\n\n3. **合法性红线**：\n   - 合同内容是否违反法律法规强制性规定\n   - 是否存在无效条款（如：排除对方主要权利）\n   - 是否违反公序良俗\n\n4. **风险等级**: Critical（红线）\n\n5. **建议措辞**：\n   - \"建议核实[乙方]是否具备[XXX]资质\"\n   - \"该条款可能因违反[XXX]规定而无效\"\n",
      "is_active": 1,
      "created_at": "2026-01-27 09:53:08.040079",
      "rule_category": "custom",
      "creator_id": null,
      "priority": 0,
      "is_system": 0
    },
    {
      "id": 9,
      "name": "验收与交付条件",
      "description": "确保验收标准明确可执行",
      "content": "\n【验收与交付条件规则】\n\n1. **审查要点**：\n   - 验收标准是否具体、可衡量\n   - 验收程序是否明确\n   - 不合格的处理方式是否约定\n\n2. **常见问题**：\n   - 验收标准模糊（如\"符合行业标准\"但未明确具体标准）\n   - 验收期限不合理（如\"甲方收到后3天内验收\"）\n   - \"视为验收合格\"条款过宽\n\n3. **风险等级**: Medium\n\n4. **建议措辞**：\n   - \"建议约定具体的验收标准\"\n   - \"验收期限应合理，建议至少7个工作日\"\n   - \"慎用'视为验收合格'条款\"\n",
      "is_active": 1,
      "created_at": "2026-01-27 09:53:08.041906",
      "rule_category": "custom",
      "creator_id": null,
      "priority": 0,
      "is_system": 0
    },
    {
      "id": 10,
      "name": "保密与知识产权条款",
      "description": "保护公司核心信息和知识产权",
      "content": "\n【保密与知识产权条款规则】\n\n1. **保密条款**：\n   - 是否明确约定保密信息的范围\n   - 保密期限是否合理（建议不少于合同终止后3年）\n   - 违反保密责任的违约责任是否明确\n\n2. **知识产权条款**：\n   - 明确合同履行过程中产生的知识产权归属\n   - 对于委托开发，应明确约定知识产权归属\n   - 避免默认知识产权归对方所有\n\n3. **红线预警**：\n   - 无保密条款\n   - 知识产权约定不明导致公司权益受损\n\n4. **风险等级**: Medium\n\n5. **建议措辞**：\n   - \"建议补充保密条款\"\n   - \"建议明确约定本合同产生的知识产权归[甲方]所有\"\n",
      "is_active": 1,
      "created_at": "2026-01-27 09:53:08.043722",
      "rule_category": "custom",
      "creator_id": null,
      "priority": 0,
      "is_system": 0
    },
    {
      "id": 11,
      "name": "解除与终止条款",
      "description": "确保合同解除条件公平合理",
      "content": "\n【解除与终止条款规则】\n\n1. **审查要点**：\n   - 解除条件是否具体、明确\n   - 双方解除权是否对等\n   - 合同终止后的处理是否约定\n\n2. **常见问题**：\n   - 仅一方享有解除权\n   - 解除条件模糊（如\"严重影响\"未定义）\n   - 无合同终止后的善后处理条款\n\n3. **红线预警**：\n   - \"甲方不得解除本合同\"等绝对化条款\n   - 解除通知期过短\n\n4. **风险等级**: High\n\n5. **建议措辞**：\n   - \"建议赋予双方平等的解除权\"\n   - \"建议约定明确的解除条件\"\n   - \"建议补充合同终止后的善后处理条款\"\n",
      "is_active": 1,
      "created_at": "2026-01-27 09:53:08.045783",
      "rule_category": "custom",
      "creator_id": null,
      "priority": 0,
      "is_system": 0
    },
    {
      "id": 12,
      "name": "不可抗力条款",
      "description": "确保不可抗力条款公平合理",
      "content": "\n【不可抗力条款规则】\n\n1. **审查要点**：\n   - 不可抗力的定义是否合理\n   - 通知义务是否明确\n   - 减损义务是否约定\n\n2. **常见问题**：\n   - 不可抗力范围过窄或过宽\n   - 无通知期限约定\n   - 未约定减损义务\n\n3. **风险等级**: Low\n\n4. **建议措辞**：\n   - \"建议补充不可抗力条款\"\n   - \"建议约定明确的不可抗力通知期限（如3日内）\"\n   - \"建议约定不可抗力发生后的减损义务\"\n",
      "is_active": 1,
      "created_at": "2026-01-27 09:53:08.047481",
      "rule_category": "custom",
      "creator_id": null,
      "priority": 0,
      "is_system": 0
    },
    {
      "id": 13,
      "name": "[转移所有权] 交付节点",
      "description": "特征: 交易性质 > 转移所有权",
      "content": "必须明确所有权转移的时间点（交付时或付清款项时）以及风险转移节点。",
      "is_active": 1,
      "created_at": "2026-01-27 10:08:12.614640",
      "rule_category": "feature",
      "creator_id": null,
      "priority": 10,
      "is_system": 1
    },
    {
      "id": 14,
      "name": "[转移所有权] 瑕疵担保",
      "description": "特征: 交易性质 > 转移所有权",
      "content": "审查转让方是否对标的物的权利瑕疵（如抵押、查封）和质量瑕疵做出了担保承诺。",
      "is_active": 1,
      "created_at": "2026-01-27 10:08:12.616718",
      "rule_category": "feature",
      "creator_id": null,
      "priority": 10,
      "is_system": 1
    },
    {
      "id": 15,
      "name": "[提供服务] 验收标准",
      "description": "特征: 交易性质 > 提供服务",
      "content": "必须包含具体的服务验收标准（如SLA、交付物清单）或量化指标，避免'满意为止'等模糊表述。",
      "is_active": 1,
      "created_at": "2026-01-27 10:08:12.618635",
      "rule_category": "feature",
      "creator_id": null,
      "priority": 10,
      "is_system": 1
    },
    {
      "id": 16,
      "name": "[提供服务] 服务变更",
      "description": "特征: 交易性质 > 提供服务",
      "content": "审查服务范围变更的触发条件及费用调整机制（Change Request流程）。",
      "is_active": 1,
      "created_at": "2026-01-27 10:08:12.620541",
      "rule_category": "feature",
      "creator_id": null,
      "priority": 10,
      "is_system": 1
    },
    {
      "id": 17,
      "name": "[许可使用] 授权范围",
      "description": "特征: 交易性质 > 许可使用",
      "content": "必须明确许可的地域（全球/国内）、期限、是否独占、是否可转授权（Sub-license）。",
      "is_active": 1,
      "created_at": "2026-01-27 10:08:12.622402",
      "rule_category": "feature",
      "creator_id": null,
      "priority": 10,
      "is_system": 1
    },
    {
      "id": 18,
      "name": "[许可使用] 侵权责任",
      "description": "特征: 交易性质 > 许可使用",
      "content": "审查若授权标的侵犯第三方权利，授权方应承担的赔偿责任。",
      "is_active": 1,
      "created_at": "2026-01-27 10:08:12.624935",
      "rule_category": "feature",
      "creator_id": null,
      "priority": 10,
      "is_system": 1
    },
    {
      "id": 19,
      "name": "[租赁使用] 租赁期限",
      "description": "特征: 交易性质 > 租赁使用",
      "content": "审查租赁期限是否超过20年（法律规定上限）。",
      "is_active": 1,
      "created_at": "2026-01-27 10:08:12.626999",
      "rule_category": "feature",
      "creator_id": null,
      "priority": 10,
      "is_system": 1
    },
    {
      "id": 20,
      "name": "[租赁使用] 修缮义务",
      "description": "特征: 交易性质 > 租赁使用",
      "content": "明确租赁物损坏时的维修责任承担方（出租人修还是承租人修）。",
      "is_active": 1,
      "created_at": "2026-01-27 10:08:12.629278",
      "rule_category": "feature",
      "creator_id": null,
      "priority": 10,
      "is_system": 1
    },
    {
      "id": 21,
      "name": "[租赁使用] 返还状态",
      "description": "特征: 交易性质 > 租赁使用",
      "content": "明确期满返还时的状态要求（恢复原状还是现状交还）。",
      "is_active": 1,
      "created_at": "2026-01-27 10:08:12.631076",
      "rule_category": "feature",
      "creator_id": null,
      "priority": 10,
      "is_system": 1
    },
    {
      "id": 22,
      "name": "[借款融资] 利息合规",
      "description": "特征: 交易性质 > 借款融资",
      "content": "审查借款利率是否超过法定上限（如LPR的4倍）。",
      "is_active": 1,
      "created_at": "2026-01-27 10:08:12.633082",
      "rule_category": "feature",
      "creator_id": null,
      "priority": 10,
      "is_system": 1
    },
    {
      "id": 23,
      "name": "[借款融资] 提前还款",
      "description": "特征: 交易性质 > 借款融资",
      "content": "明确借款人是否可以提前还款，以及提前还款是否需要支付违约金。",
      "is_active": 1,
      "created_at": "2026-01-27 10:08:12.634763",
      "rule_category": "feature",
      "creator_id": null,
      "priority": 10,
      "is_system": 1
    },
    {
      "id": 24,
      "name": "[劳动用工] 法定权益",
      "description": "特征: 交易性质 > 劳动用工",
      "content": "必须包含社保缴纳、工时制度、劳动保护等法定条款，严禁约定'放弃社保'。",
      "is_active": 1,
      "created_at": "2026-01-27 10:08:12.636215",
      "rule_category": "feature",
      "creator_id": null,
      "priority": 10,
      "is_system": 1
    },
    {
      "id": 25,
      "name": "[劳动用工] 试用期",
      "description": "特征: 交易性质 > 劳动用工",
      "content": "审查试用期时长是否符合合同期限对应的法定标准。",
      "is_active": 1,
      "created_at": "2026-01-27 10:08:12.637811",
      "rule_category": "feature",
      "creator_id": null,
      "priority": 10,
      "is_system": 1
    },
    {
      "id": 26,
      "name": "[不动产] 登记过户",
      "description": "特征: 合同标的 > 不动产",
      "content": "审查是否包含不动产登记过户的义务、时间节点及税费承担条款。",
      "is_active": 1,
      "created_at": "2026-01-27 10:08:12.639609",
      "rule_category": "feature",
      "creator_id": null,
      "priority": 10,
      "is_system": 1
    },
    {
      "id": 27,
      "name": "[动产] 物流运输",
      "description": "特征: 合同标的 > 动产",
      "content": "明确运输方式、运费承担方及运输途中的损耗承担。",
      "is_active": 1,
      "created_at": "2026-01-27 10:08:12.641264",
      "rule_category": "feature",
      "creator_id": null,
      "priority": 10,
      "is_system": 1
    },
    {
      "id": 28,
      "name": "[智力成果] IP归属",
      "description": "特征: 合同标的 > 智力成果",
      "content": "明确成果产生后的知识产权归属（委托方拥有、受托方拥有或共有）。",
      "is_active": 1,
      "created_at": "2026-01-27 10:08:12.642800",
      "rule_category": "feature",
      "creator_id": null,
      "priority": 10,
      "is_system": 1
    },
    {
      "id": 29,
      "name": "[智力成果] 背景知识产权",
      "description": "特征: 合同标的 > 智力成果",
      "content": "区分原有的背景IP和新产生的增量IP。",
      "is_active": 1,
      "created_at": "2026-01-27 10:08:12.644726",
      "rule_category": "feature",
      "creator_id": null,
      "priority": 10,
      "is_system": 1
    },
    {
      "id": 30,
      "name": "[资金] 支付路径",
      "description": "特征: 合同标的 > 资金",
      "content": "审查收款账户信息是否准确，是否约定了发票开具与付款的先后顺序（先票后款）。",
      "is_active": 1,
      "created_at": "2026-01-27 10:08:12.646574",
      "rule_category": "feature",
      "creator_id": null,
      "priority": 10,
      "is_system": 1
    },
    {
      "id": 31,
      "name": "[劳动力] 人身安全",
      "description": "特征: 合同标的 > 劳动力",
      "content": "涉及劳动力提供的，应关注劳动保护及工伤责任的约定。",
      "is_active": 1,
      "created_at": "2026-01-27 10:08:12.648138",
      "rule_category": "feature",
      "creator_id": null,
      "priority": 10,
      "is_system": 1
    },
    {
      "id": 32,
      "name": "[行业-外商投资] 审批备案",
      "description": "外商投资企业需办理审批或备案手续",
      "content": "审查外商投资协议是否包含：1. 投资准入负面清单核查；2. 行业主管部门审批/备案条款；3. 外汇登记手续约定；4. 安全审查申报义务",
      "is_active": 1,
      "created_at": "2026-01-27 10:08:12.649991",
      "rule_category": "industry",
      "creator_id": null,
      "priority": 100,
      "is_system": 1
    },
    {
      "id": 33,
      "name": "[行业-建筑工程] 资质证书",
      "description": "建筑工程需审查承包方资质",
      "content": "审查建筑工程合同是否包含：1. 承包方资质等级要求；2. 施工许可证办理约定；3. 工程质量标准明确；4. 安全生产责任划分；5. 竣工验收程序",
      "is_active": 1,
      "created_at": "2026-01-27 10:08:12.651727",
      "rule_category": "industry",
      "creator_id": null,
      "priority": 101,
      "is_system": 1
    },
    {
      "id": 34,
      "name": "[行业-房地产] 开发资质",
      "description": "房地产开发需审查开发资质和土地权属",
      "content": "审查房地产合同是否包含：1. 开发商资质证书要求；2. 国有土地使用证复印件；3. 建设工程规划许可证；4. 预售许可证（如适用）；5. 面积差异处理条款",
      "is_active": 1,
      "created_at": "2026-01-27 10:08:12.653331",
      "rule_category": "industry",
      "creator_id": null,
      "priority": 102,
      "is_system": 1
    },
    {
      "id": 35,
      "name": "[行业-金融] 利率合规",
      "description": "金融借款合同需审查利率合规性",
      "content": "审查金融借款合同是否包含：1. 年化利率不超过法定上限（LPR的4倍）；2. 禁止砍头息条款；3. 费用透明化要求；4. 逾期利息和违约金合理约定；5. 个人信息授权条款",
      "is_active": 1,
      "created_at": "2026-01-27 10:08:12.655031",
      "rule_category": "industry",
      "creator_id": null,
      "priority": 103,
      "is_system": 1
    },
    {
      "id": 36,
      "name": "[行业-劳动] 社保公积金",
      "description": "劳动合同需审查社保公积金缴纳",
      "content": "审查劳动合同是否包含：1. 社保公积金缴纳基数和比例；2. 加班工资计算标准；3. 年休假安排；4. 竞业限制补偿金；5. 解除劳动合同经济补偿",
      "is_active": 1,
      "created_at": "2026-01-27 10:08:12.656762",
      "rule_category": "industry",
      "creator_id": null,
      "priority": 104,
      "is_system": 1
    },
    {
      "id": 37,
      "name": "[行业-医疗器械] 注册证照",
      "description": "医疗器械需审查注册证和经营许可",
      "content": "审查医疗器械合同是否包含：1. 医疗器械注册证有效期限；2. 经营许可证范围核查；3. 质量保证条款；4. 不良事件报告义务；5. 召回和赔偿责任",
      "is_active": 1,
      "created_at": "2026-01-27 10:08:12.658500",
      "rule_category": "industry",
      "creator_id": null,
      "priority": 105,
      "is_system": 1
    },
    {
      "id": 38,
      "name": "[行业-教育] 办学许可",
      "description": "教育培训需审查办学资质",
      "content": "审查教育培训合同是否包含：1. 办学许可证有效期限；2. 收费标准和退费条款；3. 教师资质要求；4. 安全保障责任；5. 教学质量保证",
      "is_active": 1,
      "created_at": "2026-01-27 10:08:12.660096",
      "rule_category": "industry",
      "creator_id": null,
      "priority": 106,
      "is_system": 1
    },
    {
      "id": 39,
      "name": "[行业-电商] 平台责任",
      "description": "电商合同需审查平台责任和数据合规",
      "content": "审查电商合同是否包含：1. 平台资质和ICP备案；2. 用户个人信息保护条款；3. 消费者权益保护承诺；4. 知识产权侵权处理；5. 七日无理由退货适用",
      "is_active": 1,
      "created_at": "2026-01-27 10:08:12.661818",
      "rule_category": "industry",
      "creator_id": null,
      "priority": 107,
      "is_system": 1
    },
    {
      "id": 40,
      "name": "[party_a] 付款控制",
      "description": "立场: party_a",
      "content": "作为甲方，审查付款条款是否挂钩具体的交付节点或验收合格结果（坚持'先验收后付款'）。",
      "is_active": 1,
      "created_at": "2026-01-27 10:08:12.663627",
      "rule_category": "stance",
      "creator_id": null,
      "priority": 20,
      "is_system": 1
    },
    {
      "id": 41,
      "name": "[party_a] 解约权",
      "description": "立场: party_a",
      "content": "确保甲方在乙方严重违约或逾期时拥有单方解除合同的权利。",
      "is_active": 1,
      "created_at": "2026-01-27 10:08:12.665241",
      "rule_category": "stance",
      "creator_id": null,
      "priority": 20,
      "is_system": 1
    },
    {
      "id": 42,
      "name": "[party_a] 赔偿兜底",
      "description": "立场: party_a",
      "content": "尽量避免接受乙方的赔偿责任上限（Liability Cap），或要求上限至少覆盖合同总额。",
      "is_active": 1,
      "created_at": "2026-01-27 10:08:12.668178",
      "rule_category": "stance",
      "creator_id": null,
      "priority": 20,
      "is_system": 1
    },
    {
      "id": 43,
      "name": "[party_b] 收款安全",
      "description": "立场: party_b",
      "content": "作为乙方，审查付款时间是否明确。争取约定'预付款'或'逾期付款违约金'。",
      "is_active": 1,
      "created_at": "2026-01-27 10:08:12.670380",
      "rule_category": "stance",
      "creator_id": null,
      "priority": 20,
      "is_system": 1
    },
    {
      "id": 44,
      "name": "[party_b] 免责机制",
      "description": "立场: party_b",
      "content": "争取加入'因甲方原因或第三方原因导致延期，乙方不承担责任'的条款。",
      "is_active": 1,
      "created_at": "2026-01-27 10:08:12.672801",
      "rule_category": "stance",
      "creator_id": null,
      "priority": 20,
      "is_system": 1
    },
    {
      "id": 45,
      "name": "[party_b] 责任封顶",
      "description": "立场: party_b",
      "content": "强烈建议设定违约赔偿上限（例如不超过合同金额的X%），避免无限连带责任。",
      "is_active": 1,
      "created_at": "2026-01-27 10:08:12.675143",
      "rule_category": "stance",
      "creator_id": null,
      "priority": 20,
      "is_system": 1
    },
    {
      "id": 46,
      "name": "[通用] U01",
      "description": "形式质量",
      "content": "审查全文是否存在错别字、标点错误、金额大小写不一致、日期逻辑错误（如结束日期早于开始日期）。",
      "is_active": 1,
      "created_at": "2026-01-27 10:08:12.677079",
      "rule_category": "universal",
      "creator_id": null,
      "priority": 0,
      "is_system": 1
    },
    {
      "id": 47,
      "name": "[通用] U02",
      "description": "定义一致性",
      "content": "检查合同中定义的术语（如'产品'、'服务'）在后文使用中是否保持含义一致，是否存在前后矛盾。",
      "is_active": 1,
      "created_at": "2026-01-27 10:08:12.679057",
      "rule_category": "universal",
      "creator_id": null,
      "priority": 0,
      "is_system": 1
    },
    {
      "id": 48,
      "name": "[通用] U03",
      "description": "争议解决",
      "content": "审查争议解决条款是否明确且可执行。若约定仲裁，必须有具体的仲裁委员会名称；若约定诉讼，管辖法院必须符合法定规则。",
      "is_active": 1,
      "created_at": "2026-01-27 10:08:12.680990",
      "rule_category": "universal",
      "creator_id": null,
      "priority": 0,
      "is_system": 1
    },
    {
      "id": 49,
      "name": "[通用] U04",
      "description": "通知送达",
      "content": "检查是否包含法律文书送达地址条款，且地址信息是否具体，是否约定了电子送达方式。",
      "is_active": 1,
      "created_at": "2026-01-27 10:08:12.683136",
      "rule_category": "universal",
      "creator_id": null,
      "priority": 0,
      "is_system": 1
    },
    {
      "id": 50,
      "name": "[通用] 预付款比例红线",
      "description": "控制预付款比例，降低资金风险",
      "content": "\n【预付款比例红线规则】\n\n1. **基本原则**：预付款比例原则上不得超过合同总额的30%。\n\n2. **特殊情况例外**：\n   - 对于大型设备采购或工程建设，经特别批准可放宽至50%\n   - 必须有明确的付款节点和验收标准\n\n3. **审查要点**：\n   - 检查合同中预付款比例是否超过30%（或经批准的50%）\n   - 预付款是否与明确的里程碑或验收条件挂钩\n   - 是否存在\"全额预付\"等高风险条款\n\n4. **风险等级**: Critical（红线）\n\n5. **建议措辞**：\n   - \"预付款比例过高，建议不超过合同总额的30%\"\n   - \"预付款应与明确的验收节点挂钩\"\n",
      "is_active": 1,
      "created_at": "2026-01-27 10:08:12.685083",
      "rule_category": "universal",
      "creator_id": null,
      "priority": 0,
      "is_system": 1
    },
    {
      "id": 51,
      "name": "[通用] 争议解决条款",
      "description": "确保争议解决方式对公司有利",
      "content": "\n【争议解决条款规则】\n\n1. **优先顺序**：\n   - 第一选择：约定在\"甲方所在地法院\"诉讼\n   - 第二选择：约定在特定仲裁委员会（如北京仲裁委员会、上海仲裁委员会）仲裁\n   - 禁止接受：被告所在地法院、对方所在地仲裁\n\n2. **审查要点**：\n   - 检查争议解决条款是否明确\n   - 管辖法院/仲裁机构是否对公司有利\n   - 是否存在\"或裁或审\"等无效约定\n\n3. **风险等级**: High\n\n4. **建议措辞**：\n   - \"因本合同引起的争议，应提交甲方所在地人民法院诉讼解决\"\n   - \"争议提交北京仲裁委员会，按照申请仲裁时该会现行有效的仲裁规则进行仲裁\"\n",
      "is_active": 1,
      "created_at": "2026-01-27 10:08:12.686773",
      "rule_category": "universal",
      "creator_id": null,
      "priority": 0,
      "is_system": 1
    },
    {
      "id": 52,
      "name": "[通用] 违约责任完整性",
      "description": "确保双方违约责任对等且具体",
      "content": "\n【违约责任完整性规则】\n\n1. **核心原则**：双方违约责任应当对等、具体、可执行。\n\n2. **审查要点**：\n   - 是否明确约定了双方的违约情形\n   - 违约金计算方式是否具体（如：每日万分之五）\n   - 是否存在\"甲方不承担违约责任\"等不对等条款\n   - 违约金是否过高或过低（一般不超过合同总额的30%）\n\n3. **红线预警**：\n   - 仅约定乙方违约责任，甲方无违约责任\n   - 违约金条款模糊不清（如\"承担相应责任\"）\n   - 免责条款过宽（如\"甲方对任何损失不承担责任\"）\n\n4. **风险等级**: High（红线预警）\n\n5. **建议措辞**：\n   - \"双方均应严格履行合同义务，任何一方违约应承担相应违约责任\"\n   - \"违约方应向守约方支付违约金，计算方式为：[具体计算公式]\"\n",
      "is_active": 1,
      "created_at": "2026-01-27 10:08:12.688383",
      "rule_category": "universal",
      "creator_id": null,
      "priority": 0,
      "is_system": 1
    },
    {
      "id": 53,
      "name": "[通用] 合同性质与类型认定",
      "description": "明确合同法律性质，确保适用正确法规",
      "content": "\n【合同性质与类型认定规则】\n\n1. **典型合同类型**（基于《民法典》）：\n   - 买卖合同、供用电水气热合同、赠与合同\n   - 借款合同、保证合同、租赁合同、融资租赁合同\n   - 保理合同、承揽合同、建设工程合同\n   - 运输合同、技术合同、保管合同、仓储合同\n   - 委托合同、物业服务合同、行纪合同、中介合同、合伙合同\n\n2. **审查要点**：\n   - 通读全文，判断合同属于哪种典型合同\n   - 如不属于典型合同，应明确其基础法律关系\n   - 检查合同名称与实际内容是否一致\n\n3. **特殊风险**：\n   - \"名为合作实为借贷\"：需警惕虚假表示\n   - \"名为买卖实为融资\"：警惕融资性贸易风险\n\n4. **风险等级**: Medium\n\n5. **建议措辞**：\n   - \"本合同性质为[XXX]合同，应遵循《民法典》关于[XXX]合同的专门规定\"\n   - \"合同名称与内容不一致，建议修改合同名称以反映实际法律关系\"\n",
      "is_active": 1,
      "created_at": "2026-01-27 10:08:12.690084",
      "rule_category": "universal",
      "creator_id": null,
      "priority": 0,
      "is_system": 1
    },
    {
      "id": 54,
      "name": "[通用] 条款完备性检查",
      "description": "确保核心条款齐备",
      "content": "\n【条款完备性检查规则】\n\n1. **必备条款清单**：\n   - 标的物/服务内容\n   - 数量与质量标准\n   - 价款或报酬\n   - 履行期限、地点、方式\n   - 违约责任\n   - 争议解决方式\n\n2. **审查要点**：\n   - 逐一核对必备条款是否齐备\n   - 检查是否存在\"另行协商\"等模糊表述导致条款缺失\n   - 关键条款是否具体明确\n\n3. **常见缺失**：\n   - 质量标准不明确\n   - 履行期限模糊\n   - 违约责任约定不清\n\n4. **风险等级**: Medium\n\n5. **建议措辞**：\n   - \"建议补充明确[XXX]的具体标准\"\n   - \"建议约定明确的履行期限\"\n",
      "is_active": 1,
      "created_at": "2026-01-27 10:08:12.691974",
      "rule_category": "universal",
      "creator_id": null,
      "priority": 0,
      "is_system": 1
    },
    {
      "id": 55,
      "name": "[通用] 条款逻辑一致性",
      "description": "检查条款间是否存在矛盾或歧义",
      "content": "\n【条款逻辑一致性规则】\n\n1. **矛盾检查**：\n   - 同一事项在不同条款中表述是否一致\n   - 数字、日期、金额等关键信息是否前后一致\n   - 权利义务是否对等\n\n2. **常见矛盾类型**：\n   - 价格条款：前文\"固定总价\"，后文\"按实结算\"\n   - 期限条款：前文\"1年有效期\"，后文\"2年质保期\"\n   - 支付条款：前文\"月结\"，后文\"季结\"\n\n3. **歧义检查**：\n   - 语言表述是否清晰\n   - 是否存在多义词导致理解困难\n   - 专业术语是否有定义\n\n4. **风险等级**: Medium\n\n5. **建议措辞**：\n   - \"条款[XXX]与[YYY]存在矛盾，建议统一\"\n   - \"表述存在歧义，建议明确[XXX]的具体含义\"\n",
      "is_active": 1,
      "created_at": "2026-01-27 10:08:12.693640",
      "rule_category": "universal",
      "creator_id": null,
      "priority": 0,
      "is_system": 1
    },
    {
      "id": 56,
      "name": "[通用] 金额准确性核查",
      "description": "确保金额表述准确无误",
      "content": "\n【金额准确性核查规则】\n\n1. **核查要点**：\n   - 大小写金额是否一致\n   - 计算公式是否正确\n   - 单位是否明确（元/万元/美元）\n   - 是否含税（增值税税率）\n\n2. **常见错误**：\n   - 大小写不一致\n   - 计算错误（如：单价×数量≠总价）\n   - 税费承担约定不明\n\n3. **红线预警**：\n   - 金额表述模糊（如\"相关费用\"、\"合理费用\"）\n   - 费用承担方不明确\n\n4. **风险等级**: High（金额错误）\n\n5. **建议措辞**：\n   - \"大小写金额不一致，请核实\"\n   - \"建议明确费用承担方\"\n   - \"建议明确是否含税及税率\"\n",
      "is_active": 1,
      "created_at": "2026-01-27 10:08:12.695110",
      "rule_category": "universal",
      "creator_id": null,
      "priority": 0,
      "is_system": 1
    },
    {
      "id": 57,
      "name": "[通用] 主体资格与合法性",
      "description": "确保合同主体具备相应资质",
      "content": "\n【主体资格与合法性规则】\n\n1. **审查要点**：\n   - 合同主体是否具备签署该类合同的资质\n   - 是否需要特殊许可（如建筑资质、特许经营许可）\n   - 是否存在超越经营范围的情况\n\n2. **高风险行业**：\n   - 建筑工程：需检查建筑业企业资质证书\n   - 医疗器械：需检查医疗器械经营许可证\n   - 教育培训：需检查办学许可证\n   - 金融业务：需检查金融许可证\n\n3. **合法性红线**：\n   - 合同内容是否违反法律法规强制性规定\n   - 是否存在无效条款（如：排除对方主要权利）\n   - 是否违反公序良俗\n\n4. **风险等级**: Critical（红线）\n\n5. **建议措辞**：\n   - \"建议核实[乙方]是否具备[XXX]资质\"\n   - \"该条款可能因违反[XXX]规定而无效\"\n",
      "is_active": 1,
      "created_at": "2026-01-27 10:08:12.696846",
      "rule_category": "universal",
      "creator_id": null,
      "priority": 0,
      "is_system": 1
    },
    {
      "id": 58,
      "name": "[通用] 验收与交付条件",
      "description": "确保验收标准明确可执行",
      "content": "\n【验收与交付条件规则】\n\n1. **审查要点**：\n   - 验收标准是否具体、可衡量\n   - 验收程序是否明确\n   - 不合格的处理方式是否约定\n\n2. **常见问题**：\n   - 验收标准模糊（如\"符合行业标准\"但未明确具体标准）\n   - 验收期限不合理（如\"甲方收到后3天内验收\"）\n   - \"视为验收合格\"条款过宽\n\n3. **风险等级**: Medium\n\n4. **建议措辞**：\n   - \"建议约定具体的验收标准\"\n   - \"验收期限应合理，建议至少7个工作日\"\n   - \"慎用'视为验收合格'条款\"\n",
      "is_active": 1,
      "created_at": "2026-01-27 10:08:12.699189",
      "rule_category": "universal",
      "creator_id": null,
      "priority": 0,
      "is_system": 1
    },
    {
      "id": 59,
      "name": "[通用] 保密与知识产权条款",
      "description": "保护公司核心信息和知识产权",
      "content": "\n【保密与知识产权条款规则】\n\n1. **保密条款**：\n   - 是否明确约定保密信息的范围\n   - 保密期限是否合理（建议不少于合同终止后3年）\n   - 违反保密责任的违约责任是否明确\n\n2. **知识产权条款**：\n   - 明确合同履行过程中产生的知识产权归属\n   - 对于委托开发，应明确约定知识产权归属\n   - 避免默认知识产权归对方所有\n\n3. **红线预警**：\n   - 无保密条款\n   - 知识产权约定不明导致公司权益受损\n\n4. **风险等级**: Medium\n\n5. **建议措辞**：\n   - \"建议补充保密条款\"\n   - \"建议明确约定本合同产生的知识产权归[甲方]所有\"\n",
      "is_active": 1,
      "created_at": "2026-01-27 10:08:12.700975",
      "rule_category": "universal",
      "creator_id": null,
      "priority": 0,
      "is_system": 1
    },
    {
      "id": 60,
      "name": "[通用] 解除与终止条款",
      "description": "确保合同解除条件公平合理",
      "content": "\n【解除与终止条款规则】\n\n1. **审查要点**：\n   - 解除条件是否具体、明确\n   - 双方解除权是否对等\n   - 合同终止后的处理是否约定\n\n2. **常见问题**：\n   - 仅一方享有解除权\n   - 解除条件模糊（如\"严重影响\"未定义）\n   - 无合同终止后的善后处理条款\n\n3. **红线预警**：\n   - \"甲方不得解除本合同\"等绝对化条款\n   - 解除通知期过短\n\n4. **风险等级**: High\n\n5. **建议措辞**：\n   - \"建议赋予双方平等的解除权\"\n   - \"建议约定明确的解除条件\"\n   - \"建议补充合同终止后的善后处理条款\"\n",
      "is_active": 1,
      "created_at": "2026-01-27 10:08:12.702664",
      "rule_category": "universal",
      "creator_id": null,
      "priority": 0,
      "is_system": 1
    },
    {
      "id": 61,
      "name": "[通用] 不可抗力条款",
      "description": "确保不可抗力条款公平合理",
      "content": "\n【不可抗力条款规则】\n\n1. **审查要点**：\n   - 不可抗力的定义是否合理\n   - 通知义务是否明确\n   - 减损义务是否约定\n\n2. **常见问题**：\n   - 不可抗力范围过窄或过宽\n   - 无通知期限约定\n   - 未约定减损义务\n\n3. **风险等级**: Low\n\n4. **建议措辞**：\n   - \"建议补充不可抗力条款\"\n   - \"建议约定明确的不可抗力通知期限（如3日内）\"\n   - \"建议约定不可抗力发生后的减损义务\"\n",
      "is_active": 1,
      "created_at": "2026-01-27 10:08:12.704354",
      "rule_category": "universal",
      "creator_id": null,
      "priority": 0,
      "is_system": 1
    }
  ]
}